aind_dynamic_foraging_data_utils/__init__.py
aind_dynamic_foraging_data_utils/alignment.py
aind_dynamic_foraging_data_utils/code_ocean_utils.py
aind_dynamic_foraging_data_utils/enrich_dfs.py
aind_dynamic_foraging_data_utils/nwb_utils.py
aind_dynamic_foraging_data_utils-0.1.40.dist-info/licenses/LICENSE
aind_dynamic_foraging_data_utils-0.1.40.dist-info/METADATA
aind_dynamic_foraging_data_utils-0.1.40.dist-info/WHEEL
aind_dynamic_foraging_data_utils-0.1.40.dist-info/top_level.txt
aind_dynamic_foraging_data_utils-0.1.40.dist-info/RECORD
