Metadata-Version: 2.4
Name: aind-dynamic-foraging-data-utils
Version: 0.1.40
Summary: Functions to help with postprocessing dynamic foraging data.
Author: Allen Institute for Neural Dynamics
License: MIT
Classifier: Programming Language :: Python :: 3
Requires-Python: >=3.9
License-File: LICENSE
Requires-Dist: pandas
Requires-Dist: numpy
Requires-Dist: pynwb
Requires-Dist: hdmf_zarr
Requires-Dist: aind-data-access-api
Requires-Dist: codeocean
Provides-Extra: dev
Requires-Dist: black; extra == "dev"
Requires-Dist: coverage; extra == "dev"
Requires-Dist: flake8; extra == "dev"
Requires-Dist: interrogate; extra == "dev"
Requires-Dist: isort; extra == "dev"
Requires-Dist: Sphinx; extra == "dev"
Requires-Dist: furo; extra == "dev"
Dynamic: license-file
